cykooz.rehash-1.0.1.dist-info/METADATA
cykooz.rehash-1.0.1.dist-info/WHEEL
cykooz.rehash-1.0.1.dist-info/licenses/LICENSE
cykooz/rehash/rust_lib.pyi
cykooz/rehash/__init__.py
cykooz/__init__.py
cykooz/rehash/rust_lib.cpython-39-darwin.so
cykooz.rehash-1.0.1.dist-info/RECORD
