Metadata-Version: 2.3
Name: cykooz.rehash
Version: 1.0.1
Classifier: Development Status :: 5 - Production/Stable
Classifier: Programming Language :: Python
Classifier: Programming Language :: Python :: 3
Classifier: Programming Language :: Python :: 3.8
Classifier: Programming Language :: Python :: 3.9
Classifier: Programming Language :: Python :: 3.10
Classifier: Programming Language :: Python :: 3.11
Classifier: Programming Language :: Python :: 3.12
Classifier: Programming Language :: Python :: Implementation :: CPython
Classifier: Programming Language :: Rust
Classifier: Topic :: Software Development :: Libraries :: Python Modules
Classifier: License :: OSI Approved :: BSD License
Requires-Dist: wheel ; extra == 'dev'
Requires-Dist: maturin ; extra == 'dev'
Requires-Dist: pytest ; extra == 'dev'
Requires-Dist: pytest-benchmark ; extra == 'dev'
Requires-Dist: tabulate ; extra == 'dev'
Requires-Dist: patchelf ; sys_platform == 'linux' and extra == 'dev'
Provides-Extra: dev
License-File: LICENSE
Summary: A resumable implementation of SHA1 hasher
Keywords: sha1,resumable
Author: Kirill Kuzminykh <cykooz@gmail.com>
Author-email: Kirill Kuzminykh <cykooz@gmail.com>
Requires-Python: >=3.8
